seEvo1D/__init__.py
seEvo1D/__main__.py
seEvo1D/externalPlots.py
seEvo1D/mainView.py
seEvo1D/seEvo_analytical_model_1D.py
seEvo1D/seEvo_evolution_init.py
seEvo1D/seEvo_evolution_loop_1D.py
seEvo1D/seEvo_evolution_loop_1D_binned.py
seEvo1D/wmean.py
seEvo1D/workspace.py
seEvo1D-1.7.5.dist-info/LICENSE
seEvo1D-1.7.5.dist-info/METADATA
seEvo1D-1.7.5.dist-info/WHEEL
seEvo1D-1.7.5.dist-info/entry_points.txt
seEvo1D-1.7.5.dist-info/top_level.txt
seEvo1D-1.7.5.dist-info/RECORD
